{
  "last_updated": "2026-04-09 domingo 20:00",
  "is_real_data": true,
  "weeks": [
    { "key": "w4", "label": "Semana atual (7–13 Abr)" },
    { "key": "w3", "label": "Semana passada (31 Mar–6 Abr)" },
    { "key": "w2", "label": "2 semanas atrás (24–30 Mar)" },
    { "key": "w1", "label": "3 semanas atrás (17–23 Mar)" }
  ],
  "athletes": {
    "bruno": {
      "name": "Bruno Trevisan",
      "kpis":      { "ctl": 72, "atl": 68, "tsb": 4,   "tss_week": 412 },
      "kpi_delta": { "ctl": "+3", "atl": "+8", "tsb": "-4", "tss_week": "+31" },
      "pmc": {
        "labels": ["S1","S2","S3","S4","S5","S6","S7","S8"],
        "ctl":    [58, 61, 65, 68, 70, 74, 73, 72],
        "atl":    [62, 70, 75, 72, 65, 78, 74, 68],
        "tsb":    [-4, -9,-10, -4,  5, -4, -1,  4]
      },
      "zones": {
        "labels": ["Natação","Bike","Corrida"],
        "z1":     [72, 68, 65],
        "z2":     [22, 25, 28],
        "z3":     [ 6,  7,  7]
      },
      "vol": { "swim": 2.1, "bike": 5.8, "run": 3.2, "strength": 1.0 },
      "hrv": {
        "labels":   ["1/4","2/4","3/4","4/4","5/4","6/4","7/4","8/4","9/4","10/4","11/4","12/4","13/4","14/4"],
        "vals":     [56, 54, 57, 59, 55, 53, 58, 60, 57, 54, 55, 58, 59, 60],
        "baseline": 57
      },
      "adherence": [
        { "label": "Natação", "done": 2.1, "target": 2.5, "color": "#4a9eff" },
        { "label": "Bike",    "done": 5.8, "target": 6.0, "color": "#f5a623" },
        { "label": "Corrida", "done": 3.2, "target": 3.5, "color": "#4db87a" },
        { "label": "Força",   "done": 1.0, "target": 1.0, "color": "#9b8fff" }
      ],
      "alerts": [
        { "type": "ok",   "msg": "Forma positiva — TSB +4, bom momento para treinos de qualidade" },
        { "type": "info", "msg": "ATL elevada — monitorar recuperação nos próximos 3 dias" }
      ],
      "sessions": [
        { "day": "Seg", "sport": "run",      "desc": "Limiar duplo — 3×10min Z2 + 2×8min Z3", "dur": "1h15", "tss": 82,  "zones": "60/30/10", "hrv": 58, "ht": "up" },
        { "day": "Seg", "sport": "strength", "desc": "Força — Alfredson + squat unilateral",   "dur": "45min","tss": 35,  "zones": "—",        "hrv": 58, "ht": "up" },
        { "day": "Ter", "sport": "swim",     "desc": "Volume Z1 — 3.200m aeróbico",            "dur": "1h05", "tss": 48,  "zones": "80/18/2",  "hrv": 55, "ht": "dn" },
        { "day": "Qua", "sport": "bike",     "desc": "Endurance Z1 — 90min fundo",             "dur": "1h30", "tss": 65,  "zones": "75/22/3",  "hrv": 54, "ht": "nt" },
        { "day": "Qui", "sport": "run",      "desc": "Limiar duplo — 4×6min Z2 + 3×5min Z3",  "dur": "1h10", "tss": 78,  "zones": "55/32/13", "hrv": 56, "ht": "up" },
        { "day": "Sex", "sport": "swim",     "desc": "CSS — 8×100m no limiar",                 "dur": "55min","tss": 55,  "zones": "40/42/18", "hrv": 57, "ht": "up" },
        { "day": "Sáb", "sport": "bike",     "desc": "Longa Z1 — 3h base aeróbica",            "dur": "3h00", "tss": 95,  "zones": "80/18/2",  "hrv": 59, "ht": "up" }
      ]
    },
    "jean": {
      "name": "Jean Romano",
      "kpis":      { "ctl": 85, "atl": 79, "tsb": 6,   "tss_week": 498 },
      "kpi_delta": { "ctl": "+5", "atl": "+6", "tsb": "+2", "tss_week": "+44" },
      "pmc": {
        "labels": ["S1","S2","S3","S4","S5","S6","S7","S8"],
        "ctl":    [68, 72, 76, 79, 82, 85, 84, 85],
        "atl":    [70, 78, 82, 80, 76, 88, 82, 79],
        "tsb":    [-2, -6, -6, -1,  6, -3,  2,  6]
      },
      "zones": {
        "labels": ["Natação","Bike","Corrida"],
        "z1":     [70, 65, 60],
        "z2":     [24, 28, 32],
        "z3":     [ 6,  7,  8]
      },
      "vol": { "swim": 2.8, "bike": 7.2, "run": 4.5, "strength": 1.0 },
      "hrv": {
        "labels":   ["1/4","2/4","3/4","4/4","5/4","6/4","7/4","8/4","9/4","10/4","11/4","12/4","13/4","14/4"],
        "vals":     [60, 62, 61, 58, 60, 63, 64, 62, 59, 61, 63, 64, 63, 65],
        "baseline": 62
      },
      "adherence": [
        { "label": "Natação", "done": 2.8, "target": 3.0, "color": "#4a9eff" },
        { "label": "Bike",    "done": 7.2, "target": 7.0, "color": "#f5a623" },
        { "label": "Corrida", "done": 4.5, "target": 4.5, "color": "#4db87a" },
        { "label": "Força",   "done": 1.0, "target": 1.0, "color": "#9b8fff" }
      ],
      "alerts": [
        { "type": "ok",   "msg": "Excelente aderência — 97% do plano executado esta semana" },
        { "type": "info", "msg": "Buenos Aires (70.3) em 25 semanas — momento de base aeróbica" }
      ],
      "sessions": [
        { "day": "Seg", "sport": "bike",     "desc": "Limiar duplo — 5×8min Z2 + 3×6min Z3", "dur": "1h30", "tss": 95,  "zones": "50/36/14", "hrv": 62, "ht": "up" },
        { "day": "Ter", "sport": "swim",     "desc": "Técnica + CSS — 3.600m",               "dur": "1h10", "tss": 58,  "zones": "65/28/7",  "hrv": 60, "ht": "nt" },
        { "day": "Qua", "sport": "run",      "desc": "Volume Z1 — 12km fácil",               "dur": "1h15", "tss": 62,  "zones": "78/20/2",  "hrv": 61, "ht": "up" },
        { "day": "Qua", "sport": "strength", "desc": "Força funcional + mobilidade",          "dur": "45min","tss": 30,  "zones": "—",        "hrv": 61, "ht": "up" },
        { "day": "Qui", "sport": "bike",     "desc": "Limiar duplo — FTP intervals",          "dur": "1h20", "tss": 88,  "zones": "45/38/17", "hrv": 59, "ht": "dn" },
        { "day": "Sex", "sport": "swim",     "desc": "Endurance — 4.000m Z1/Z2",             "dur": "1h20", "tss": 65,  "zones": "70/26/4",  "hrv": 62, "ht": "up" },
        { "day": "Sáb", "sport": "run",      "desc": "Longa Z1/Z2 — 18km progressivo",       "dur": "1h45", "tss": 100, "zones": "65/28/7",  "hrv": 64, "ht": "up" }
      ]
    },
    "gabriel": {
      "name": "Gabriel",
      "kpis":      { "ctl": 58, "atl": 72, "tsb": -14, "tss_week": 380 },
      "kpi_delta": { "ctl": "+2", "atl": "+14", "tsb": "-12", "tss_week": "+55" },
      "pmc": {
        "labels": ["S1","S2","S3","S4","S5","S6","S7","S8"],
        "ctl":    [46, 49, 52, 54, 56, 58, 57, 58],
        "atl":    [50, 55, 60, 58, 52, 65, 70, 72],
        "tsb":    [-4, -6, -8, -4,  4, -7,-13,-14]
      },
      "zones": {
        "labels": ["Bike","Corrida","Força"],
        "z1":     [60, 58, 55],
        "z2":     [28, 30, 30],
        "z3":     [12, 12, 15]
      },
      "vol": { "swim": 0, "bike": 5.5, "run": 4.2, "strength": 1.5 },
      "hrv": {
        "labels":   ["1/4","2/4","3/4","4/4","5/4","6/4","7/4","8/4","9/4","10/4","11/4","12/4","13/4","14/4"],
        "vals":     [58, 56, 54, 52, 55, 53, 51, 50, 52, 51, 53, 54, 55, 53],
        "baseline": 55
      },
      "adherence": [
        { "label": "Bike",    "done": 5.5, "target": 5.0, "color": "#f5a623" },
        { "label": "Corrida", "done": 4.2, "target": 4.0, "color": "#4db87a" },
        { "label": "Força",   "done": 1.5, "target": 1.5, "color": "#9b8fff" }
      ],
      "alerts": [
        { "type": "danger", "msg": "Risco de overtraining — TSB −14, ATL 24% acima da CTL" },
        { "type": "warn",   "msg": "HRV em queda há 7 dias — priorizar sono e recuperação" }
      ],
      "sessions": [
        { "day": "Seg", "sport": "run",      "desc": "Limiar — 3×10min Z2 pré-duatlon",        "dur": "1h00", "tss": 70,  "zones": "55/33/12", "hrv": 52, "ht": "dn" },
        { "day": "Ter", "sport": "bike",     "desc": "Específico duatlon — 3×8min Z3",         "dur": "1h10", "tss": 85,  "zones": "40/38/22", "hrv": 50, "ht": "dn" },
        { "day": "Qua", "sport": "strength", "desc": "Alfredson + estabilização joelho",        "dur": "40min","tss": 25,  "zones": "—",        "hrv": 51, "ht": "nt" },
        { "day": "Qui", "sport": "run",      "desc": "Taper ativo — 6km Z1 leve",              "dur": "40min","tss": 35,  "zones": "85/13/2",  "hrv": 54, "ht": "up" },
        { "day": "Sex", "sport": "bike",     "desc": "Ativação pré-prova — 30min Z1 + strides","dur": "30min","tss": 22,  "zones": "80/15/5",  "hrv": 55, "ht": "up" },
        { "day": "Sáb", "sport": "run",      "desc": "PROVA — Duatlon 5/20/2.5km",             "dur": "~56min","tss":110, "zones": "20/35/45", "hrv": 53, "ht": "nt" }
      ]
    }
  }
}
